[{"name":"dav4jvm","description":null,"location":"index.html","searchKeys":["dav4jvm"]},{"name":"at.bitfire.dav4jvm","description":null,"location":"dav4jvm/at.bitfire.dav4jvm/index.html","searchKeys":["at.bitfire.dav4jvm"]},{"name":"BasicDigestAuthHandler","description":null,"location":"dav4jvm/at.bitfire.dav4jvm/-basic-digest-auth-handler/index.html","searchKeys":["BasicDigestAuthHandler"]},{"name":"Dav4jvm","description":null,"location":"dav4jvm/at.bitfire.dav4jvm/-dav4jvm/index.html","searchKeys":["Dav4jvm"]},{"name":"DavAddressBook","description":null,"location":"dav4jvm/at.bitfire.dav4jvm/-dav-address-book/index.html","searchKeys":["DavAddressBook"]},{"name":"DavCalendar","description":null,"location":"dav4jvm/at.bitfire.dav4jvm/-dav-calendar/index.html","searchKeys":["DavCalendar"]},{"name":"DavCollection","description":null,"location":"dav4jvm/at.bitfire.dav4jvm/-dav-collection/index.html","searchKeys":["DavCollection"]},{"name":"DavResource","description":null,"location":"dav4jvm/at.bitfire.dav4jvm/-dav-resource/index.html","searchKeys":["DavResource"]},{"name":"Error","description":null,"location":"dav4jvm/at.bitfire.dav4jvm/-error/index.html","searchKeys":["Error"]},{"name":"HttpUtils","description":null,"location":"dav4jvm/at.bitfire.dav4jvm/-http-utils/index.html","searchKeys":["HttpUtils"]},{"name":"Property","description":null,"location":"dav4jvm/at.bitfire.dav4jvm/-property/index.html","searchKeys":["Property"]},{"name":"PropertyFactory","description":null,"location":"dav4jvm/at.bitfire.dav4jvm/-property-factory/index.html","searchKeys":["PropertyFactory"]},{"name":"PropertyRegistry","description":null,"location":"dav4jvm/at.bitfire.dav4jvm/-property-registry/index.html","searchKeys":["PropertyRegistry"]},{"name":"PropStat","description":null,"location":"dav4jvm/at.bitfire.dav4jvm/-prop-stat/index.html","searchKeys":["PropStat"]},{"name":"QuotedStringUtils","description":null,"location":"dav4jvm/at.bitfire.dav4jvm/-quoted-string-utils/index.html","searchKeys":["QuotedStringUtils"]},{"name":"Response","description":null,"location":"dav4jvm/at.bitfire.dav4jvm/-response/index.html","searchKeys":["Response"]},{"name":"UrlUtils","description":null,"location":"dav4jvm/at.bitfire.dav4jvm/-url-utils/index.html","searchKeys":["UrlUtils"]},{"name":"XmlUtils","description":null,"location":"dav4jvm/at.bitfire.dav4jvm/-xml-utils/index.html","searchKeys":["XmlUtils"]},{"name":"at.bitfire.dav4jvm.exception","description":null,"location":"dav4jvm/at.bitfire.dav4jvm.exception/index.html","searchKeys":["at.bitfire.dav4jvm.exception"]},{"name":"ConflictException","description":null,"location":"dav4jvm/at.bitfire.dav4jvm.exception/-conflict-exception/index.html","searchKeys":["ConflictException"]},{"name":"DavException","description":null,"location":"dav4jvm/at.bitfire.dav4jvm.exception/-dav-exception/index.html","searchKeys":["DavException"]},{"name":"ForbiddenException","description":null,"location":"dav4jvm/at.bitfire.dav4jvm.exception/-forbidden-exception/index.html","searchKeys":["ForbiddenException"]},{"name":"GoneException","description":null,"location":"dav4jvm/at.bitfire.dav4jvm.exception/-gone-exception/index.html","searchKeys":["GoneException"]},{"name":"HttpException","description":null,"location":"dav4jvm/at.bitfire.dav4jvm.exception/-http-exception/index.html","searchKeys":["HttpException"]},{"name":"NotFoundException","description":null,"location":"dav4jvm/at.bitfire.dav4jvm.exception/-not-found-exception/index.html","searchKeys":["NotFoundException"]},{"name":"PreconditionFailedException","description":null,"location":"dav4jvm/at.bitfire.dav4jvm.exception/-precondition-failed-exception/index.html","searchKeys":["PreconditionFailedException"]},{"name":"ServiceUnavailableException","description":null,"location":"dav4jvm/at.bitfire.dav4jvm.exception/-service-unavailable-exception/index.html","searchKeys":["ServiceUnavailableException"]},{"name":"UnauthorizedException","description":null,"location":"dav4jvm/at.bitfire.dav4jvm.exception/-unauthorized-exception/index.html","searchKeys":["UnauthorizedException"]},{"name":"at.bitfire.dav4jvm.property","description":null,"location":"dav4jvm/at.bitfire.dav4jvm.property/index.html","searchKeys":["at.bitfire.dav4jvm.property"]},{"name":"AddMember","description":null,"location":"dav4jvm/at.bitfire.dav4jvm.property/-add-member/index.html","searchKeys":["AddMember"]},{"name":"AddressbookDescription","description":null,"location":"dav4jvm/at.bitfire.dav4jvm.property/-addressbook-description/index.html","searchKeys":["AddressbookDescription"]},{"name":"AddressbookHomeSet","description":null,"location":"dav4jvm/at.bitfire.dav4jvm.property/-addressbook-home-set/index.html","searchKeys":["AddressbookHomeSet"]},{"name":"AddressData","description":null,"location":"dav4jvm/at.bitfire.dav4jvm.property/-address-data/index.html","searchKeys":["AddressData"]},{"name":"CalendarColor","description":null,"location":"dav4jvm/at.bitfire.dav4jvm.property/-calendar-color/index.html","searchKeys":["CalendarColor"]},{"name":"CalendarData","description":null,"location":"dav4jvm/at.bitfire.dav4jvm.property/-calendar-data/index.html","searchKeys":["CalendarData"]},{"name":"CalendarDescription","description":null,"location":"dav4jvm/at.bitfire.dav4jvm.property/-calendar-description/index.html","searchKeys":["CalendarDescription"]},{"name":"CalendarHomeSet","description":null,"location":"dav4jvm/at.bitfire.dav4jvm.property/-calendar-home-set/index.html","searchKeys":["CalendarHomeSet"]},{"name":"CalendarProxyReadFor","description":null,"location":"dav4jvm/at.bitfire.dav4jvm.property/-calendar-proxy-read-for/index.html","searchKeys":["CalendarProxyReadFor"]},{"name":"CalendarProxyWriteFor","description":null,"location":"dav4jvm/at.bitfire.dav4jvm.property/-calendar-proxy-write-for/index.html","searchKeys":["CalendarProxyWriteFor"]},{"name":"CalendarTimezone","description":null,"location":"dav4jvm/at.bitfire.dav4jvm.property/-calendar-timezone/index.html","searchKeys":["CalendarTimezone"]},{"name":"CalendarUserAddressSet","description":null,"location":"dav4jvm/at.bitfire.dav4jvm.property/-calendar-user-address-set/index.html","searchKeys":["CalendarUserAddressSet"]},{"name":"CreationDate","description":null,"location":"dav4jvm/at.bitfire.dav4jvm.property/-creation-date/index.html","searchKeys":["CreationDate"]},{"name":"CurrentUserPrincipal","description":null,"location":"dav4jvm/at.bitfire.dav4jvm.property/-current-user-principal/index.html","searchKeys":["CurrentUserPrincipal"]},{"name":"CurrentUserPrivilegeSet","description":null,"location":"dav4jvm/at.bitfire.dav4jvm.property/-current-user-privilege-set/index.html","searchKeys":["CurrentUserPrivilegeSet"]},{"name":"DisplayName","description":null,"location":"dav4jvm/at.bitfire.dav4jvm.property/-display-name/index.html","searchKeys":["DisplayName"]},{"name":"GetContentLength","description":null,"location":"dav4jvm/at.bitfire.dav4jvm.property/-get-content-length/index.html","searchKeys":["GetContentLength"]},{"name":"GetContentType","description":null,"location":"dav4jvm/at.bitfire.dav4jvm.property/-get-content-type/index.html","searchKeys":["GetContentType"]},{"name":"GetCTag","description":null,"location":"dav4jvm/at.bitfire.dav4jvm.property/-get-c-tag/index.html","searchKeys":["GetCTag"]},{"name":"GetETag","description":null,"location":"dav4jvm/at.bitfire.dav4jvm.property/-get-e-tag/index.html","searchKeys":["GetETag"]},{"name":"GetLastModified","description":null,"location":"dav4jvm/at.bitfire.dav4jvm.property/-get-last-modified/index.html","searchKeys":["GetLastModified"]},{"name":"GroupMembership","description":null,"location":"dav4jvm/at.bitfire.dav4jvm.property/-group-membership/index.html","searchKeys":["GroupMembership"]},{"name":"HrefListProperty","description":null,"location":"dav4jvm/at.bitfire.dav4jvm.property/-href-list-property/index.html","searchKeys":["HrefListProperty"]},{"name":"MaxICalendarSize","description":null,"location":"dav4jvm/at.bitfire.dav4jvm.property/-max-i-calendar-size/index.html","searchKeys":["MaxICalendarSize"]},{"name":"MaxVCardSize","description":null,"location":"dav4jvm/at.bitfire.dav4jvm.property/-max-v-card-size/index.html","searchKeys":["MaxVCardSize"]},{"name":"Owner","description":null,"location":"dav4jvm/at.bitfire.dav4jvm.property/-owner/index.html","searchKeys":["Owner"]},{"name":"QuotaAvailableBytes","description":null,"location":"dav4jvm/at.bitfire.dav4jvm.property/-quota-available-bytes/index.html","searchKeys":["QuotaAvailableBytes"]},{"name":"QuotaUsedBytes","description":null,"location":"dav4jvm/at.bitfire.dav4jvm.property/-quota-used-bytes/index.html","searchKeys":["QuotaUsedBytes"]},{"name":"ResourceType","description":null,"location":"dav4jvm/at.bitfire.dav4jvm.property/-resource-type/index.html","searchKeys":["ResourceType"]},{"name":"ScheduleTag","description":null,"location":"dav4jvm/at.bitfire.dav4jvm.property/-schedule-tag/index.html","searchKeys":["ScheduleTag"]},{"name":"Source","description":null,"location":"dav4jvm/at.bitfire.dav4jvm.property/-source/index.html","searchKeys":["Source"]},{"name":"SupportedAddressData","description":null,"location":"dav4jvm/at.bitfire.dav4jvm.property/-supported-address-data/index.html","searchKeys":["SupportedAddressData"]},{"name":"SupportedCalendarComponentSet","description":null,"location":"dav4jvm/at.bitfire.dav4jvm.property/-supported-calendar-component-set/index.html","searchKeys":["SupportedCalendarComponentSet"]},{"name":"SupportedCalendarData","description":null,"location":"dav4jvm/at.bitfire.dav4jvm.property/-supported-calendar-data/index.html","searchKeys":["SupportedCalendarData"]},{"name":"SupportedReportSet","description":null,"location":"dav4jvm/at.bitfire.dav4jvm.property/-supported-report-set/index.html","searchKeys":["SupportedReportSet"]},{"name":"SyncToken","description":null,"location":"dav4jvm/at.bitfire.dav4jvm.property/-sync-token/index.html","searchKeys":["SyncToken"]}]
